README.md
setup.cfg
setup.py
src/button/__init__.py
src/button/cli.py
src/button/tasks.py
src/button.egg-info/PKG-INFO
src/button.egg-info/SOURCES.txt
src/button.egg-info/dependency_links.txt
src/button.egg-info/entry_points.txt
src/button.egg-info/top_level.txt